fix_author/__init__.py
fix_author/cli.py
fix_author/parser.py
fix_author-1.1.dist-info/METADATA
fix_author-1.1.dist-info/RECORD
fix_author-1.1.dist-info/WHEEL
fix_author-1.1.dist-info/entry_points.txt
fix_author-1.1.dist-info/top_level.txt
