Metadata-Version: 2.1
Name: fix-author
Version: 1.1
Summary: fix author info in git commits
Home-page: https://github.com/thautwarm/fix-author
Author: thautwarm
Author-email: twshere@outlook.com
License: MIT
Keywords: git commit,fix author
Platform: any
Classifier: Programming Language :: Python :: 3.6
Classifier: Programming Language :: Python :: 3.7
Classifier: Programming Language :: Python :: Implementation :: CPython
Requires-Python: >=3.6.0
Requires-Dist: rbnf
Requires-Dist: wisepy
